grasshopper/__init__.py
grasshopper/common/__init__.py
grasshopper/common/common.py
grasshopper/config/__init__.py
grasshopper/config/configloader.py
grasshopper/modbus/__init__.py
grasshopper/modbus/connection.py
grasshopper/modbus/connector.py
iot_grasshopper-1.0.9.dist-info/METADATA
iot_grasshopper-1.0.9.dist-info/WHEEL
iot_grasshopper-1.0.9.dist-info/licenses/LICENSE
iot_grasshopper-1.0.9.dist-info/RECORD
