Metadata-Version: 2.1
Name: iot-grasshopper
Version: 1.0.9
Summary: Grasshopper makes you jump higher on AWS IoT Greengrass.
Project-URL: Homepage, https://github.com/binchoo/iot-grasshopper
Project-URL: Bug Tracker, https://github.com/binchoo/iot-grasshopper/issues
Author-email: Jaebin Joo <jbinchoo@gmail.com>
License-File: LICENSE
Classifier: License :: OSI Approved :: GNU General Public License v3 (GPLv3)
Classifier: Operating System :: OS Independent
Classifier: Programming Language :: Python :: 3
Requires-Python: >=3.3
